{"seed": 8, "Data statistics": "{0: {0: 203, 1: 192, 2: 16, 3: 83, 4: 114, 5: 18, 6: 94, 7: 95, 8: 101, 9: 209}, 1: {0: 4, 1: 47, 2: 2, 3: 182, 4: 793, 5: 105, 6: 157, 7: 12, 8: 176, 9: 472}, 2: {0: 163, 1: 15, 2: 135, 3: 19, 4: 245, 5: 180, 6: 236, 7: 254, 8: 345, 9: 6}, 3: {0: 11, 1: 209, 2: 98, 3: 76, 4: 1, 5: 97, 6: 207, 7: 193, 8: 159, 9: 1782}, 4: {0: 8, 1: 115, 2: 23, 4: 782, 5: 211, 6: 46, 7: 291, 8: 37, 9: 1}, 5: {0: 21, 1: 62, 2: 168, 3: 7, 4: 288, 5: 52, 6: 137, 7: 24, 8: 447, 9: 550}, 6: {0: 65, 1: 65, 2: 3, 3: 18, 4: 393, 5: 161, 6: 16, 7: 699, 8: 270, 9: 71}, 7: {0: 1304, 1: 164, 2: 119, 3: 670}, 8: {0: 153, 1: 4, 2: 289, 3: 150, 4: 49, 5: 13, 6: 126, 7: 5, 8: 177, 9: 664}, 9: {0: 9, 1: 60, 2: 68, 3: 41, 4: 7, 5: 46, 6: 36, 7: 81, 8: 3, 9: 347}, 10: {0: 255, 1: 393, 3: 315, 4: 3, 5: 463, 6: 157, 7: 996}, 11: {0: 20, 1: 2, 2: 417, 3: 467, 4: 41, 5: 1, 6: 755, 7: 10, 8: 65, 9: 33}, 12: {0: 1198, 1: 96, 2: 19, 3: 17, 4: 211, 5: 209, 6: 61, 7: 68, 8: 504}, 13: {0: 986, 1: 47, 2: 17, 3: 1, 5: 48, 6: 41, 7: 126, 8: 667}, 14: {0: 58, 1: 76, 2: 984, 3: 698, 4: 68, 5: 17, 6: 96, 7: 288}, 15: {0: 1, 1: 3, 2: 2, 3: 41, 4: 8, 5: 2250}, 16: {1: 2, 2: 481, 3: 293, 4: 226, 5: 873, 6: 392}, 17: {0: 29, 1: 25, 2: 156, 3: 704, 4: 532, 5: 8, 6: 1, 7: 20, 8: 1382}, 18: {0: 11, 1: 226, 3: 9, 4: 369, 5: 24, 6: 202, 7: 255, 8: 104, 9: 275}, 19: {0: 162, 1: 1, 2: 1127, 3: 3, 4: 1, 5: 21, 6: 9, 7: 20, 8: 166, 9: 201}, 20: {0: 7, 1: 2435}, 21: {0: 21, 1: 611, 2: 8, 3: 189, 4: 223, 5: 85, 6: 160, 7: 256, 8: 20, 9: 22}, 22: {0: 275, 1: 18, 2: 3, 3: 744, 4: 427, 5: 111, 6: 337, 7: 986}, 23: {1: 7, 2: 797, 3: 149, 4: 218, 5: 6, 6: 1262}, 24: {0: 36, 1: 125, 2: 68, 3: 124, 4: 1, 5: 1, 6: 472, 7: 321, 8: 377, 9: 367}}", "loading time": 70, "local_train_accs": [0.5031111111111111, 0.6635897435897435, 0.4818523153942428, 0.7133780444758206, 0.6393659180977543, 0.6412300683371298, 0.5877342419080068, 0.7284005316792203, 0.6012269938650306, 0.5873925501432665, 0.6405886909372579, 0.6449475427940364, 0.599664288711708, 0.7201241593378168, 0.5943107221006565, 0.9770065075921909, 0.537273930304367, 0.736436821841092, 0.5613559322033899, 0.7691408533021625, 0.9971334971334971, 0.6100313479623825, 0.5822130299896587, 0.6760967609676096, 0.5988372093023255], "local_test_accs": [0.2829, 0.2714, 0.2431, 0.216, 0.2141, 0.2671, 0.2499, 0.1546, 0.2752, 0.174, 0.2753, 0.2098, 0.1903, 0.2162, 0.1707, 0.1002, 0.1759, 0.2049, 0.2831, 0.2088, 0.1, 0.2431, 0.2411, 0.1537, 0.2613], "Uniform ensemble (Train acc)": 0.39734, "Uniform ensemble (Test acc)": 0.3917, "FedAvg (Train acc)": 0.1, "FedAvg (Test acc)": 0.1, "pdm_KL_reg 0": {"Best Result": {"Best Sigma0": 10, "Best sigma": 1, "Best gamma": 50, "Best Test accuracy": 0.214, "Train acc": 0.21188}, "PDM log": "{(10, 1, 50): {'shapes': [(3072, 700), (700,), (700, 10), (10,)], 'train_accuracy': 0.21188, 'test_accuracy': 0.214}}", "timing": 676}, "pdm_KL_reg 0.001": {"Best Result": {"Best Sigma0": 10, "Best sigma": 1, "Best gamma": 50, "Best Test accuracy": 0.2279, "Train acc": 0.223}, "PDM log": "{(10, 1, 50): {'shapes': [(3072, 700), (700,), (700, 10), (10,)], 'train_accuracy': 0.223, 'test_accuracy': 0.2279}}", "timing": 1398}, "pdm_KL_reg 0.005": {"Best Result": {"Best Sigma0": 10, "Best sigma": 1, "Best gamma": 50, "Best Test accuracy": 0.2362, "Train acc": 0.2283}, "PDM log": "{(10, 1, 50): {'shapes': [(3072, 700), (700,), (700, 10), (10,)], 'train_accuracy': 0.2283, 'test_accuracy': 0.2362}}", "timing": 1197}, "pdm_KL_reg 0.01": {"Best Result": {"Best Sigma0": 10, "Best sigma": 1, "Best gamma": 50, "Best Test accuracy": 0.2417, "Train acc": 0.2345}, "PDM log": "{(10, 1, 50): {'shapes': [(3072, 700), (700,), (700, 10), (10,)], 'train_accuracy': 0.2345, 'test_accuracy': 0.2417}}", "timing": 1241}, "pdm_KL_reg 0.05": {"Best Result": {"Best Sigma0": 10, "Best sigma": 1, "Best gamma": 50, "Best Test accuracy": 0.222, "Train acc": 0.2187}, "PDM log": "{(10, 1, 50): {'shapes': [(3072, 700), (700,), (700, 10), (10,)], 'train_accuracy': 0.2187, 'test_accuracy': 0.222}}", "timing": 1103}, "pdm_KL_reg 0.1": {"Best Result": {"Best Sigma0": 10, "Best sigma": 1, "Best gamma": 50, "Best Test accuracy": 0.2407, "Train acc": 0.2344}, "PDM log": "{(10, 1, 50): {'shapes': [(3072, 700), (700,), (700, 10), (10,)], 'train_accuracy': 0.2344, 'test_accuracy': 0.2407}}", "timing": 1133}, "pdm_KL_reg 0.5": {"Best Result": {"Best Sigma0": 10, "Best sigma": 1, "Best gamma": 50, "Best Test accuracy": 0.3056, "Train acc": 0.30698}, "PDM log": "{(10, 1, 50): {'shapes': [(3072, 700), (700,), (700, 10), (10,)], 'train_accuracy': 0.30698, 'test_accuracy': 0.3056}}", "timing": 1216}, "pdm_KL_reg 1": {"Best Result": {"Best Sigma0": 10, "Best sigma": 1, "Best gamma": 50, "Best Test accuracy": 0.2221, "Train acc": 0.2179}, "PDM log": "{(10, 1, 50): {'shapes': [(3072, 422), (422,), (422, 10), (10,)], 'train_accuracy': 0.2179, 'test_accuracy': 0.2221}}", "timing": 816}, "pdm_KL_reg 2": {"Best Result": {"Best Sigma0": 10, "Best sigma": 1, "Best gamma": 50, "Best Test accuracy": 0.1141, "Train acc": 0.1138}, "PDM log": "{(10, 1, 50): {'shapes': [(3072, 144), (144,), (144, 10), (10,)], 'train_accuracy': 0.1138, 'test_accuracy': 0.1141}}", "timing": 262}, "pdm_KL_reg 5": {"Best Result": {"Best Sigma0": 10, "Best sigma": 1, "Best gamma": 50, "Best Test accuracy": 0.1, "Train acc": 0.1}, "PDM log": "{(10, 1, 50): {'shapes': [(3072, 123), (123,), (123, 10), (10,)], 'train_accuracy': 0.1, 'test_accuracy': 0.1}}", "timing": 183}, "pdm_KL_reg 10": {"Best Result": {"Best Sigma0": 10, "Best sigma": 1, "Best gamma": 50, "Best Test accuracy": 0.1, "Train acc": 0.1}, "PDM log": "{(10, 1, 50): {'shapes': [(3072, 121), (121,), (121, 10), (10,)], 'train_accuracy': 0.1, 'test_accuracy': 0.1}}", "timing": 164}, "best_reg": 0.5}