{"seed": 1, "Data statistics": "{0: {0: 510, 1: 492, 2: 515, 3: 474, 4: 530, 5: 498, 6: 501, 7: 489, 8: 481, 9: 510}, 1: {0: 476, 1: 494, 2: 523, 3: 515, 4: 477, 5: 497, 6: 486, 7: 523, 8: 497, 9: 512}, 2: {0: 503, 1: 524, 2: 501, 3: 526, 4: 471, 5: 497, 6: 538, 7: 499, 8: 482, 9: 459}, 3: {0: 484, 1: 501, 2: 514, 3: 480, 4: 487, 5: 513, 6: 529, 7: 501, 8: 480, 9: 511}, 4: {0: 506, 1: 496, 2: 478, 3: 495, 4: 492, 5: 512, 6: 520, 7: 487, 8: 490, 9: 524}, 5: {0: 517, 1: 496, 2: 472, 3: 525, 4: 496, 5: 506, 6: 458, 7: 480, 8: 503, 9: 547}, 6: {0: 491, 1: 522, 2: 492, 3: 490, 4: 506, 5: 482, 6: 492, 7: 499, 8: 557, 9: 469}, 7: {0: 516, 1: 500, 2: 499, 3: 512, 4: 523, 5: 503, 6: 468, 7: 515, 8: 493, 9: 471}, 8: {0: 503, 1: 497, 2: 498, 3: 492, 4: 484, 5: 490, 6: 509, 7: 511, 8: 506, 9: 510}, 9: {0: 494, 1: 478, 2: 508, 3: 491, 4: 534, 5: 502, 6: 499, 7: 496, 8: 511, 9: 487}}", "loading time": 134, "local_train_accs": [0.1982, 0.2664, 0.2142, 0.1584, 0.2784, 0.1818, 0.1908, 0.2104, 0.216, 0.213], "local_test_accs": [0.1876, 0.2406, 0.2023, 0.1581, 0.262, 0.1836, 0.1817, 0.1954, 0.1922, 0.2101], "Uniform ensemble (Train acc)": 0.25964, "Uniform ensemble (Test acc)": 0.2565, "FedAvg (Train acc)": 0.1, "FedAvg (Test acc)": 0.1, "pdm_KL_reg 0": {"Best Result": {"Best Sigma0": 0.5, "Best sigma": 1, "Best gamma": 10, "Best Test accuracy": 0.1114, "Train acc": 0.1122}, "PDM log": "{(0.5, 1, 10): {'shapes': [(3072, 241), (241,), (241, 118), (118,), (118, 118), (118,), (118, 118), (118,), (118, 118), (118,), (118, 10), (10,)], 'train_accuracy': 0.1122, 'test_accuracy': 0.1114}}", "timing": 396}, "pdm_KL_reg 0.001": {"Best Result": {"Best Sigma0": 0.5, "Best sigma": 1, "Best gamma": 10, "Best Test accuracy": 0.1169, "Train acc": 0.11222}, "PDM log": "{(0.5, 1, 10): {'shapes': [(3072, 237), (237,), (237, 118), (118,), (118, 127), (127,), (127, 127), (127,), (127, 118), (118,), (118, 10), (10,)], 'train_accuracy': 0.11222, 'test_accuracy': 0.1169}}", "timing": 744}, "pdm_KL_reg 0.005": {"Best Result": {"Best Sigma0": 0.5, "Best sigma": 1, "Best gamma": 10, "Best Test accuracy": 0.1219, "Train acc": 0.11744}, "PDM log": "{(0.5, 1, 10): {'shapes': [(3072, 241), (241,), (241, 118), (118,), (118, 118), (118,), (118, 118), (118,), (118, 118), (118,), (118, 10), (10,)], 'train_accuracy': 0.11744, 'test_accuracy': 0.1219}}", "timing": 767}, "pdm_KL_reg 0.01": {"Best Result": {"Best Sigma0": 0.5, "Best sigma": 1, "Best gamma": 10, "Best Test accuracy": 0.1098, "Train acc": 0.105}, "PDM log": "{(0.5, 1, 10): {'shapes': [(3072, 247), (247,), (247, 127), (127,), (127, 118), (118,), (118, 118), (118,), (118, 118), (118,), (118, 10), (10,)], 'train_accuracy': 0.105, 'test_accuracy': 0.1098}}", "timing": 858}, "pdm_KL_reg 0.05": {"Best Result": {"Best Sigma0": 0.5, "Best sigma": 1, "Best gamma": 10, "Best Test accuracy": 0.1022, "Train acc": 0.10106}, "PDM log": "{(0.5, 1, 10): {'shapes': [(3072, 240), (240,), (240, 127), (127,), (127, 127), (127,), (127, 118), (118,), (118, 118), (118,), (118, 10), (10,)], 'train_accuracy': 0.10106, 'test_accuracy': 0.1022}}", "timing": 716}, "pdm_KL_reg 0.1": {"Best Result": {"Best Sigma0": 0.5, "Best sigma": 1, "Best gamma": 10, "Best Test accuracy": 0.1047, "Train acc": 0.10398}, "PDM log": "{(0.5, 1, 10): {'shapes': [(3072, 241), (241,), (241, 127), (127,), (127, 118), (118,), (118, 118), (118,), (118, 118), (118,), (118, 10), (10,)], 'train_accuracy': 0.10398, 'test_accuracy': 0.1047}}", "timing": 717}, "pdm_KL_reg 0.5": {"Best Result": {"Best Sigma0": 0.5, "Best sigma": 1, "Best gamma": 10, "Best Test accuracy": 0.1275, "Train acc": 0.12272}, "PDM log": "{(0.5, 1, 10): {'shapes': [(3072, 305), (305,), (305, 127), (127,), (127, 127), (127,), (127, 127), (127,), (127, 118), (118,), (118, 10), (10,)], 'train_accuracy': 0.12272, 'test_accuracy': 0.1275}}", "timing": 754}, "pdm_KL_reg 1": {"Best Result": {"Best Sigma0": 0.5, "Best sigma": 1, "Best gamma": 10, "Best Test accuracy": 0.0991, "Train acc": 0.0994}, "PDM log": "{(0.5, 1, 10): {'shapes': [(3072, 471), (471,), (471, 127), (127,), (127, 127), (127,), (127, 127), (127,), (127, 118), (118,), (118, 10), (10,)], 'train_accuracy': 0.0994, 'test_accuracy': 0.0991}}", "timing": 1199}, "pdm_KL_reg 2": {"Best Result": {"Best Sigma0": 0.5, "Best sigma": 1, "Best gamma": 10, "Best Test accuracy": 0.1, "Train acc": 0.1}, "PDM log": "{(0.5, 1, 10): {'shapes': [(3072, 615), (615,), (615, 127), (127,), (127, 127), (127,), (127, 127), (127,), (127, 127), (127,), (127, 10), (10,)], 'train_accuracy': 0.1, 'test_accuracy': 0.1}}", "timing": 1368}, "pdm_KL_reg 5": {"Best Result": {"Best Sigma0": 0.5, "Best sigma": 1, "Best gamma": 10, "Best Test accuracy": 0.1, "Train acc": 0.1}, "PDM log": "{(0.5, 1, 10): {'shapes': [(3072, 620), (620,), (620, 136), (136,), (136, 127), (127,), (127, 136), (136,), (136, 127), (127,), (127, 10), (10,)], 'train_accuracy': 0.1, 'test_accuracy': 0.1}}", "timing": 1481}, "pdm_KL_reg 10": {"Best Result": {"Best Sigma0": 0.5, "Best sigma": 1, "Best gamma": 10, "Best Test accuracy": 0.1, "Train acc": 0.1}, "PDM log": "{(0.5, 1, 10): {'shapes': [(3072, 646), (646,), (646, 136), (136,), (136, 127), (127,), (127, 136), (136,), (136, 127), (127,), (127, 10), (10,)], 'train_accuracy': 0.1, 'test_accuracy': 0.1}}", "timing": 1354}, "best_reg": 0.5}